verysimplemodule_pedro_vitor/__init__.py
verysimplemodule_pedro_vitor/add.py
verysimplemodule_pedro_vitor/subtract.py
verysimplemodule_pedro_vitor/extra/__init__.py
verysimplemodule_pedro_vitor/extra/divide.py
verysimplemodule_pedro_vitor/extra/multiple.py
verysimplemodule_pedro_vitor-0.0.5.dist-info/METADATA
verysimplemodule_pedro_vitor-0.0.5.dist-info/WHEEL
verysimplemodule_pedro_vitor-0.0.5.dist-info/top_level.txt
verysimplemodule_pedro_vitor-0.0.5.dist-info/RECORD
